FixedEffectModelPyHDFE/AlphaStdErr.py
FixedEffectModelPyHDFE/Bootstrap.py
FixedEffectModelPyHDFE/CalDf.py
FixedEffectModelPyHDFE/CalFullModel.py
FixedEffectModelPyHDFE/ClusterErr.py
FixedEffectModelPyHDFE/DemeanDataframe.py
FixedEffectModelPyHDFE/EstimableCheck.py
FixedEffectModelPyHDFE/Forg.py
FixedEffectModelPyHDFE/FormTransfer.py
FixedEffectModelPyHDFE/GetFixedEffect.py
FixedEffectModelPyHDFE/OLSFixed.py
FixedEffectModelPyHDFE/OLSHighDCategory.py
FixedEffectModelPyHDFE/Operation.py
FixedEffectModelPyHDFE/Projection.py
FixedEffectModelPyHDFE/RobustErr.py
FixedEffectModelPyHDFE/WaldTest.py
FixedEffectModelPyHDFE/__init__.py
FixedEffectModelPyHDFE/api.py
FixedEffectModelPyHDFE/to_latex.py
FixedEffectModelPyHDFE-0.0.5.dist-info/LICENSE.txt
FixedEffectModelPyHDFE-0.0.5.dist-info/METADATA
FixedEffectModelPyHDFE-0.0.5.dist-info/WHEEL
FixedEffectModelPyHDFE-0.0.5.dist-info/top_level.txt
FixedEffectModelPyHDFE-0.0.5.dist-info/RECORD
